MANIFEST.in
README.rst
setup.py
phileo/__init__.py
phileo/admin.py
phileo/auth_backends.py
phileo/models.py
phileo/settings.py
phileo/signals.py
phileo/urls.py
phileo/utils.py
phileo/views.py
phileo.egg-info/PKG-INFO
phileo.egg-info/SOURCES.txt
phileo.egg-info/dependency_links.txt
phileo.egg-info/not-zip-safe
phileo.egg-info/top_level.txt
phileo/templates/phileo/_like.html
phileo/templates/phileo/_widget.html
phileo/templates/phileo/_widget_brief.html
phileo/templatetags/__init__.py
phileo/templatetags/phileo_tags.py
phileo/tests/__init__.py
phileo/tests/models.py
phileo/tests/test_models.py
phileo/tests/test_tags.py